rdkit_data_pipeline_tools.libs/libRDKitAlignment-b4c16c7d.so.1.2023.09.3
rdkit_data_pipeline_tools.libs/libRDKitChemTransforms-f2c852d0.so.1.2023.09.3
rdkit_data_pipeline_tools.libs/libRDKitDataStructs-d851fc49.so.1.2023.09.3
rdkit_data_pipeline_tools.libs/libRDKitDepictor-fe9ba682.so.1.2023.09.3
rdkit_data_pipeline_tools.libs/libRDKitDescriptors-d9d6bfc2.so.1.2023.09.3
rdkit_data_pipeline_tools.libs/libRDKitFingerprints-f302bbbd.so.1.2023.09.3
rdkit_data_pipeline_tools.libs/libRDKitGenericGroups-06799385.so.1.2023.09.3
rdkit_data_pipeline_tools.libs/libRDKitGraphMol-7899a3f4.so.1.2023.09.3
rdkit_data_pipeline_tools.libs/libRDKitMolAlign-100ec827.so.1.2023.09.3
rdkit_data_pipeline_tools.libs/libRDKitMolTransforms-052645fa.so.1.2023.09.3
rdkit_data_pipeline_tools.libs/libRDKitPartialCharges-b6f32cab.so.1.2023.09.3
rdkit_data_pipeline_tools.libs/libRDKitRDGeneral-71052b10.so.1.2023.09.3
rdkit_data_pipeline_tools.libs/libRDKitRDGeometryLib-eea36711.so.1.2023.09.3
rdkit_data_pipeline_tools.libs/libRDKitSmilesParse-86b1d0de.so.1.2023.09.3
rdkit_data_pipeline_tools.libs/libRDKitSubgraphs-d587e20c.so.1.2023.09.3
rdkit_data_pipeline_tools.libs/libRDKitSubstructMatch-5cbda019.so.1.2023.09.3
rdkit_data_pipeline_tools.libs/libboost_iostreams-8b3dd269.so.1.83.0
rdkit_data_pipeline_tools.libs/libboost_python312-56ff9efb.so.1.83.0
rdkit_data_pipeline_tools.libs/libboost_serialization-dded9aef.so.1.83.0
rdkit_data_pipeline_tools.libs/libbz2-218c4abd.so.1.0.4
rdkit_data_pipeline_tools.libs/libcoordgen-769a1efa.so.3.0.2
rdkit_data_pipeline_tools.libs/liblzma-a9793942.so.5.4.5
rdkit_data_pipeline_tools.libs/libmaeparser-7a3ece96.so.1.3.1
rdkit_data_pipeline_tools.libs/libzstd-0a2128bc.so.1.5.5
rdktools/__init__.py
rdktools/_rdktools_core.cpython-312-x86_64-linux-gnu.so
rdktools/rdktools_tf_ops.so
rdktools/tf_ops.py
rdktools/lib/libRDKitDataStructs.so.1.2023.09.3
rdktools/lib/libRDKitDescriptors.so.1.2023.09.3
rdkit_data_pipeline_tools-0.1.5.dist-info/METADATA
rdkit_data_pipeline_tools-0.1.5.dist-info/WHEEL
rdkit_data_pipeline_tools-0.1.5.dist-info/RECORD
