Metadata-Version: 2.1
Name: rdkit-data-pipeline-tools
Version: 0.1.5
Summary: High-performance molecular operations using RDKit's C++ core through nanobind bindings
Keywords: chemistry,cheminformatics,rdkit,molecular,descriptors
Author-Email: wuhao <wuhao@novogaia.bio>
License: MIT
Classifier: Development Status :: 4 - Beta
Classifier: Intended Audience :: Science/Research
Classifier: License :: OSI Approved :: MIT License
Classifier: Programming Language :: Python :: 3
Classifier: Programming Language :: Python :: 3.12
Classifier: Programming Language :: C++
Classifier: Topic :: Scientific/Engineering :: Chemistry
Classifier: Topic :: Scientific/Engineering :: Bio-Informatics
Requires-Python: >=3.12
Requires-Dist: numpy>=1.20.0
Requires-Dist: tensorflow==2.19.0
